Metadata-Version: 2.1
Name: quicktrash
Version: 1.0.0
Summary: EzPz Recycling
Home-page: UNKNOWN
Author: Perzan
Author-email: PerzanDevelopment@gmail.com
License: UNKNOWN
Platform: UNKNOWN
